lstm_variants/__init__.py
lstm_variants/lstm.py
lstm_variants-0.1.2.dist-info/LICENSE
lstm_variants-0.1.2.dist-info/METADATA
lstm_variants-0.1.2.dist-info/WHEEL
lstm_variants-0.1.2.dist-info/top_level.txt
lstm_variants-0.1.2.dist-info/RECORD
