Metadata-Version: 2.1
Name: lstm-variants
Version: 0.1.2
Summary: Long-Short Term Memory variants
Home-page: https://github.com/urchade/lstm-variants.git
Author: Urchade Zaratiana
Author-email: urchade.zaratiana@gmail.com
License: UNKNOWN
Platform: UNKNOWN
Classifier: Programming Language :: Python :: 3
Classifier: License :: OSI Approved :: MIT License
Classifier: Operating System :: OS Independent
Requires-Python: >=3.6
